graia/protocol/core/__init__.py
graia/protocol/core/exceptions.py
graia_protocol_core-0.0.1.dist-info/LICENSE
graia_protocol_core-0.0.1.dist-info/WHEEL
graia_protocol_core-0.0.1.dist-info/METADATA
graia_protocol_core-0.0.1.dist-info/RECORD
