Metadata-Version: 2.1
Name: graia-protocol-core
Version: 0.0.1
Summary: Abstract implementation of "Protocol" in "Graia Framework"
License: AGPL-3.0
Author: Chenwe-i-lin
Author-email: 1846913566@qq.com
Requires-Python: >=3.6,<4.0
Classifier: License :: OSI Approved :: GNU Affero General Public License v3
Classifier: Programming Language :: Python :: 3
Classifier: Programming Language :: Python :: 3.6
Classifier: Programming Language :: Python :: 3.7
Classifier: Programming Language :: Python :: 3.8
Requires-Dist: pydantic (>=1.5.1,<2.0.0)
